gesp/__init__.py
gesp/__main__.py
gesp/data/ECLI-Gerichtscodes.csv
gesp/pipelines/exporters.py
gesp/pipelines/formatters.py
gesp/pipelines/texts.py
gesp/spiders/bb.py
gesp/spiders/be.py
gesp/spiders/bund.py
gesp/spiders/bw.py
gesp/spiders/by.py
gesp/spiders/hb.py
gesp/spiders/he.py
gesp/spiders/hh.py
gesp/spiders/mv.py
gesp/spiders/ni.py
gesp/spiders/nw.py
gesp/spiders/rp.py
gesp/spiders/sh.py
gesp/spiders/sl.py
gesp/spiders/sn.py
gesp/spiders/st.py
gesp/spiders/th.py
gesp/src/config.py
gesp/src/create_file.py
gesp/src/fingerprint.py
gesp/src/get_text.py
gesp/src/htmlparser.py
gesp/src/output.py
gesp-0.2.0.dist-info/METADATA
gesp-0.2.0.dist-info/WHEEL
gesp-0.2.0.dist-info/licenses/LICENCE.md
gesp-0.2.0.dist-info/RECORD
