Metadata-Version: 2.4
Name: gesp
Version: 0.2.0
Summary: convenient scraping of german court decisions
Project-URL: Homepage, https://github.com/niklaswais/gesp
Project-URL: Bug Tracker, https://github.com/niklaswais/gesp/issues
Author-email: Niklas Wais <niklas.wais@tum.de>
License-File: LICENCE.md
Classifier: License :: OSI Approved :: MIT License
Classifier: Operating System :: OS Independent
Classifier: Programming Language :: Python :: 3
Requires-Python: >=3.8
Requires-Dist: attrs>=23.2.0
Requires-Dist: automat>=22.10.0
Requires-Dist: certifi>=2024.2.0
Requires-Dist: cffi>=1.16.0
Requires-Dist: charset-normalizer>=3.3.0
Requires-Dist: constantly>=23.10.0
Requires-Dist: cryptography>=42.0.0
Requires-Dist: cssselect>=1.2.0
Requires-Dist: filelock>=3.13.0
Requires-Dist: hyperlink>=21.0.0
Requires-Dist: idna>=3.6
Requires-Dist: incremental>=22.10.0
Requires-Dist: itemadapter>=0.8.0
Requires-Dist: itemloaders>=1.1.0
Requires-Dist: jmespath>=1.0.1
Requires-Dist: lxml>=5.1.0
Requires-Dist: parsel>=1.8.1
Requires-Dist: protego>=0.3.0
Requires-Dist: pyasn1-modules>=0.3.0
Requires-Dist: pyasn1>=0.5.1
Requires-Dist: pycparser>=2.21
Requires-Dist: pydispatcher>=2.0.7
Requires-Dist: pyopenssl>=24.0.0
Requires-Dist: queuelib>=1.6.2
Requires-Dist: requests-file>=1.5.1
Requires-Dist: requests>=2.31.0
Requires-Dist: scrapy>=2.11.0
Requires-Dist: service-identity>=24.1.0
Requires-Dist: six>=1.16.0
Requires-Dist: tldextract>=5.1.1
Requires-Dist: twisted>=24.2.0
Requires-Dist: typing-extensions>=4.9.0
Requires-Dist: urllib3>=2.2.0
Requires-Dist: w3lib>=2.1.2
Requires-Dist: zope-interface>=6.1
